{
  "name": "AL Sports Admin Panel",
  "short_name": "AL Admin",
  "description": "AL Sports staff admin panel — manage predictions, scores, players and more.",
  "start_url": "/al-sports/admin.html",
  "scope": "/al-sports/",
  "display": "standalone",
  "background_color": "#060d24",
  "theme_color": "#060d24",
  "orientation": "portrait-primary",
  "lang": "en",
  "icons": [
    {
      "src": "admin-logo.png",
      "sizes": "192x192",
      "type": "image/png",
      "purpose": "any maskable"
    },
    {
      "src": "admin-logo.png",
      "sizes": "512x512",
      "type": "image/png",
      "purpose": "any maskable"
    }
  ],
  "shortcuts": [
    {
      "name": "Dashboard",
      "short_name": "Dashboard",
      "url": "/al-sports/admin.html#dashboard",
      "icons": [{ "src": "admin-logo.png", "sizes": "96x96" }]
    },
    {
      "name": "Predictions",
      "short_name": "Predictions",
      "url": "/al-sports/admin.html#predictions",
      "icons": [{ "src": "admin-logo.png", "sizes": "96x96" }]
    }
  ]
}
